layabase/__init__.py
layabase/_api.py
layabase/_api_mongo.py
layabase/_api_sqlalchemy.py
layabase/_audit.py
layabase/_audit_mongo.py
layabase/_audit_sqlalchemy.py
layabase/_database.py
layabase/_database_mongo.py
layabase/_database_sqlalchemy.py
layabase/_exceptions.py
layabase/_versioning_mongo.py
layabase/mongo.py
layabase/testing.py
layabase/version.py
layabase-3.5.1.dist-info/LICENSE
layabase-3.5.1.dist-info/METADATA
layabase-3.5.1.dist-info/WHEEL
layabase-3.5.1.dist-info/top_level.txt
layabase-3.5.1.dist-info/RECORD
