Metadata-Version: 2.1
Name: layabase
Version: 3.5.1
Summary: Database for layab
Home-page: https://colin-b.github.io/layabase/
Author: Colin Bounouar
Author-email: colin.bounouar.dev@gmail.com
Maintainer: Colin Bounouar
Maintainer-email: colin.bounouar.dev@gmail.com
License: MIT
Download-URL: https://pypi.org/project/layabase/
Project-URL: GitHub, https://github.com/Colin-b/layabase
Project-URL: Changelog, https://github.com/Colin-b/layabase/blob/master/CHANGELOG.md
Project-URL: Issues, https://github.com/Colin-b/layabase/issues
Keywords: mongo,sqla,db,flask
Platform: Windows
Platform: Linux
Classifier: Development Status :: 5 - Production/Stable
Classifier: Intended Audience :: Developers
Classifier: License :: OSI Approved :: MIT License
Classifier: Natural Language :: English
Classifier: Programming Language :: Python
Classifier: Programming Language :: Python :: 3
Classifier: Programming Language :: Python :: 3.6
Classifier: Programming Language :: Python :: 3.7
Classifier: Programming Language :: Python :: 3.8
Classifier: Topic :: Software Development :: Build Tools
Requires-Python: >=3.6
Requires-Dist: layaberr (==2.*)
Provides-Extra: mongo
Requires-Dist: pymongo[tls] (==3.*) ; extra == 'mongo'
Requires-Dist: iso8601 (==0.1.*) ; extra == 'mongo'
Provides-Extra: sqlalchemy
Requires-Dist: marshmallow (==3.*) ; extra == 'sqlalchemy'
Requires-Dist: SQLAlchemy (==1.*) ; extra == 'sqlalchemy'
Requires-Dist: marshmallow-sqlalchemy (==0.21.*) ; extra == 'sqlalchemy'
Provides-Extra: testing
Requires-Dist: pytest-flask (==0.15.*) ; extra == 'testing'
Requires-Dist: mongomock (==3.*) ; extra == 'testing'
Requires-Dist: pytest-cov (==2.*) ; extra == 'testing'
Requires-Dist: pymongo[tls] (==3.*) ; extra == 'testing'
Requires-Dist: iso8601 (==0.1.*) ; extra == 'testing'
Requires-Dist: marshmallow (==3.*) ; extra == 'testing'
Requires-Dist: SQLAlchemy (==1.*) ; extra == 'testing'
Requires-Dist: marshmallow-sqlalchemy (==0.21.*) ; extra == 'testing'
